README.md
setup.py
activecampaign_api/__init__.py
activecampaign_api/version.py
activecampaign_api.egg-info/PKG-INFO
activecampaign_api.egg-info/SOURCES.txt
activecampaign_api.egg-info/dependency_links.txt
activecampaign_api.egg-info/top_level.txt
activecampaign_api/api/__init__.py
activecampaign_api/api/abstract_request.py
activecampaign_api/api/api.py
activecampaign_api/api/api_request.py
activecampaign_api/api/configuration.py
activecampaign_api/api/consts.py
activecampaign_api/api/contact.py
activecampaign_api/api/custom_field.py
activecampaign_api/api/custom_field_value.py
activecampaign_api/api/email_activities.py
activecampaign_api/api/message.py
activecampaign_api/api/segment.py
activecampaign_api/api/webhook.py
activecampaign_api/api/webhook_events.py