Metadata-Version: 1.0
Name: activecampaign-api
Version: 1.0.4
Summary: Api for activecampaign
Home-page: UNKNOWN
Author: Yevhen Pechurin
Author-email: yevhen.pechurin@gmail.com
License: UNKNOWN
Platform: UNKNOWN
